LICENSE.txt
MANIFEST.in
README.txt
setup.py
bin/rst2html+go.py
rstgo/__init__.py
rstgo/board.py
rstgo/parsers.py
rstgo/rst.py
rstgo/tests.py
rstgo.egg-info/PKG-INFO
rstgo.egg-info/SOURCES.txt
rstgo.egg-info/dependency_links.txt
rstgo.egg-info/requires.txt
rstgo.egg-info/top_level.txt
rstgo/examples/annotations.rst
rstgo/examples/making-good-shape.rst
rstgo/examples/rest-go-diagrams-implemented.rst
rstgo/examples/sample.rst
rstgo/resources/tiny/b-side.png
rstgo/resources/tiny/bl-corner.png
rstgo/resources/tiny/black.png
rstgo/resources/tiny/br-corner.png
rstgo/resources/tiny/empty.png
rstgo/resources/tiny/l-side.png
rstgo/resources/tiny/point.png
rstgo/resources/tiny/r-side.png
rstgo/resources/tiny/starpoint.png
rstgo/resources/tiny/t-side.png
rstgo/resources/tiny/tl-corner.png
rstgo/resources/tiny/tr-corner.png
rstgo/resources/tiny/white.png