Metadata-Version: 1.0
Name: rstgo
Version: 0.2.0
Summary: A package to render go diagrams and embed them in reStructuredText documents
Home-page: http://bitbucket.org/cliff/rstgo
Author: J. Cliff Dyer
Author-email: jcd@sdf.lonestar.org
License: LICENSE.txt
Platform: UNKNOWN
Classifier: Development Status :: 3 - Alpha
Classifier: Intended Audience :: Developers
Classifier: License :: OSI Approved :: MIT License
Classifier: Operating System :: OS Independent
Classifier: Programming Language :: Python
Classifier: Programming Language :: Python :: 2
Classifier: Topic :: Documentation
Classifier: Topic :: Games/Entertainment :: Board Games
Classifier: Topic :: Games/Entertainment :: Turn Based Strategy
